file_to_unicode_base64_data_uri.py
file_to_unicode_base64_data_uri-0.1.0a1.dist-info/licenses/LICENSE
file_to_unicode_base64_data_uri-0.1.0a1.dist-info/METADATA
file_to_unicode_base64_data_uri-0.1.0a1.dist-info/WHEEL
file_to_unicode_base64_data_uri-0.1.0a1.dist-info/top_level.txt
file_to_unicode_base64_data_uri-0.1.0a1.dist-info/RECORD
