Metadata-Version: 2.4
Name: file-to-unicode-base64-data-uri
Version: 0.1.0a1
Summary: A simple, efficient utility for converting files to Unicode base64-encoded data URIs.
Author-email: Jifeng Wu <jifengwu2k@gmail.com>
License-Expression: MIT
Project-URL: Homepage, https://github.com/jifengwu2k/file-to-unicode-base64-data-uri
Project-URL: Bug Tracker, https://github.com/jifengwu2k/file-to-unicode-base64-data-uri/issues
Classifier: Programming Language :: Python :: 2
Classifier: Programming Language :: Python :: 3
Classifier: Operating System :: OS Independent
Requires-Python: >=2
License-File: LICENSE
Requires-Dist: guess-file-mime-type
Requires-Dist: typing; python_version < "3.5"
Dynamic: license-file
